internalTools/__init__.py
internalTools/modeling/__init__.py
internalTools/modeling/functions.py
internalTools/modeling/ner_model.py
internalTools/modeling/qa_model.py
internalTools/modeling/zero_shot_model.py
internalTools/processing/__init__.py
internalTools/processing/text/__init__.py
internalTools/processing/text/constants.py
internalTools/processing/text/functions.py
internalTools/testing/testing.py
internalTools-0.0.7.dist-info/LICENSE
internalTools-0.0.7.dist-info/METADATA
internalTools-0.0.7.dist-info/WHEEL
internalTools-0.0.7.dist-info/top_level.txt
internalTools-0.0.7.dist-info/RECORD
