Metadata-Version: 2.1
Name: internalTools
Version: 0.0.7
Summary: A Library containing a set of useful functions for ML and AI development.
Author-email: Abdelrahman Yaghi <abd.a.yaghi@gmail.com>, Omar Quishawi <omaralquishawi25@gmail.com>
Maintainer-email: Abdelrahman Yaghi <abd.a.yaghi@gmail.com>, Omar Quishawi <omaralquishawi25@gmail.com>
License: MIT License
Project-URL: Homepage, https://pypi.org/project/internalTools/
Project-URL: Repository, https://github.com/AbdelRahmanYaghi/internalTools
Project-URL: Issues, https://github.com/AbdelRahmanYaghi/internalTools/issues
Classifier: Development Status :: 3 - Alpha
Classifier: Programming Language :: Python
Requires-Python: >=3.10
License-File: LICENSE
Requires-Dist: sentence-transformers==3.0.1
Requires-Dist: nltk==3.8.1
Requires-Dist: ftfy==6.2.3
Requires-Dist: transformers==4.44.2
Requires-Dist: gliner==0.2.10
